LICENSE
MANIFEST.in
README.md
requirements.txt
setup.py
crotte/__init__.py
crotte/regressors.py
crotte.egg-info/PKG-INFO
crotte.egg-info/SOURCES.txt
crotte.egg-info/dependency_links.txt
crotte.egg-info/requires.txt
crotte.egg-info/top_level.txt