Metadata-Version: 2.1
Name: crotte
Version: 0.1.3
Summary: Small personal project to learn about numpy and classes.
Home-page: https://github.com/kristin54/linreg
Author: Kristina
License: MIT
Keywords: linear regression project
Platform: UNKNOWN
Classifier: License :: OSI Approved :: MIT License
Classifier: Programming Language :: Python :: 3.7
Classifier: Programming Language :: Python :: 3.8
Classifier: Programming Language :: Python :: 3.9
Classifier: Programming Language :: Python :: 3 :: Only
License-File: LICENSE
